MANIFEST.in
README.rst
setup.py
pgmigrate2/__init__.py
pgmigrate2/api.py
pgmigrate2/db.py
pgmigrate2/main.py
pgmigrate2/repo.py
pgmigrate2.egg-info/PKG-INFO
pgmigrate2.egg-info/SOURCES.txt
pgmigrate2.egg-info/dependency_links.txt
pgmigrate2.egg-info/entry_points.txt
pgmigrate2.egg-info/not-zip-safe
pgmigrate2.egg-info/requires.txt
pgmigrate2.egg-info/top_level.txt