Metadata-Version: 1.1
Name: pgmigrate2
Version: 1.2.2
Summary: Database schema migration tool for people who do not afraid SQL
Home-page: https://bitbucket.org/shopium/pgmigrate2
Author: Sergey Kirillov
Author-email: sergey.kirillov@gmail.com
License: Apache License 2.0
Keywords: database migration tool postgres postgresql mysql sqlite
Platform: any
Classifier: Programming Language :: Python
Classifier: Operating System :: OS Independent
Classifier: Natural Language :: English
